<?xml version='1.0' encoding='UTF-8'?>
<?artifactRepository version='1.1.0'?>
<artifacts size='1'>
  <artifact classifier='osgi.bundle' id='jp.pizzafactory.mruby.builder.minirake' version='8.5.0.v20150210-0537'>
    <properties size='5'>
      <property name='artifact.size' value='8699'/>
      <property name='download.size' value='8699'/>
      <property name='maven-groupId' value='jp.pizzafactory.mruby'/>
      <property name='maven-artifactId' value='jp.pizzafactory.mruby.builder.minirake'/>
      <property name='maven-version' value='8.5.0-SNAPSHOT'/>
    </properties>
  </artifact>
</artifacts>
